watch_lite-0.1.1.dist-info/METADATA
watch_lite-0.1.1.dist-info/WHEEL
watch_lite-0.1.1.dist-info/entry_points.txt
watch_lite-0.1.1.dist-info/licenses/LICENSE
watch_lite/__init__.py
watch_lite/_core.pyd
watch_lite-0.1.1.dist-info/RECORD
