Metadata-Version: 2.4
Name: watch-lite
Version: 0.1.1
Requires-Dist: maturin >=1.7.8
License-File: LICENSE
Summary: A simple, lightweight and performant file watcher for python built with rust
Author-email: jake <jakewdr@proton.me>
Requires-Python: >=3.8
